nowcast/__init__.py
nowcast/arex.py
nowcast/data_config.py
nowcast/datasets/__init__.py
nowcast/datasets/data_loaders.py
nowcast/models/__init__.py
nowcast/models/argo_models.py
nowcast/utils/__init__.py
nowcast/utils/metrics.py
nowcast-0.1.2.dist-info/LICENSE
nowcast-0.1.2.dist-info/METADATA
nowcast-0.1.2.dist-info/WHEEL
nowcast-0.1.2.dist-info/top_level.txt
nowcast-0.1.2.dist-info/RECORD
