Metadata-Version: 2.1
Name: nowcast
Version: 0.1.2
Summary: Light, modular framework for dynamic time series modeling
Home-page: https://github.com/fl16180/nowcast
Author: Fred Lu
Author-email: fredlu.flac@gmail.com
License: GPL-3.0
Platform: UNKNOWN
Requires-Dist: numpy (>=1.17.1)
Requires-Dist: scipy (>=1.2.1)
Requires-Dist: scikit-learn (>=0.20.3)
Requires-Dist: pandas (>=0.25.1)
Requires-Dist: tqdm (>=4.36.1)
